[
    {
        "id": "group-91b2d7fa-6c3e-4b8a-9f22-7e4c1a8d2b90",
        "name": "Tech Innovators",
        "groupIcon": "/assets/imgs/groups/tech.png",
        "memberCount": 5898
    },
    {
        "id": "group-d3a7f1b2-4c9e-4f11-8b77-1c2d9e5f7a44",
        "name": "Culinary Masters",
        "groupIcon": "/assets/imgs/groups/food.png",
        "memberCount": 833
    },
    {
        "id": "group-7e9c2a11-5b44-4f8d-9c33-0a1f7d2e6c55",
        "name": "Movie Fans United",
        "groupIcon": "/assets/imgs/groups/movies.png",
        "memberCount": 892732
    },
    {
        "id": "group-2b8f4d77-1c3a-4e9f-8d11-9f0a6b3e2d88",
        "name": "Night Runners",
        "groupIcon": "/assets/imgs/groups/runners.png",
        "memberCount": 101
    }
]
